PyRobi/Clien.py
PyRobi/Copyright.py
PyRobi/Device.py
PyRobi/Encoder.py
PyRobi/Error.py
PyRobi/Getheader.py
PyRobi/GtM.py
PyRobi/PostData.py
PyRobi/PyRobi.py
PyRobi/TypeText.py
PyRobi/Zedcontent.py
PyRobi/__init__.py
PyRobiLibrary-1.0.0.dist-info/LICENCE
PyRobiLibrary-1.0.0.dist-info/METADATA
PyRobiLibrary-1.0.0.dist-info/WHEEL
PyRobiLibrary-1.0.0.dist-info/top_level.txt
PyRobiLibrary-1.0.0.dist-info/RECORD
