Metadata-Version: 2.1
Name: PyRobiLibrary
Version: 1.0.0
Summary: Library Robot Rubika
Home-page: https://github.com/Nanymous/NanyRubika.git
Author: Mohammad
Author-email: mmdim427@gmail.com
License: MIT
Keywords: NanyRubika,NanyRubika,NanyRubika,NanyRubika,bot,Bot,BOT,Robot,ROBOT,robot,self,api,API,Api,rubika,Rubika,RUBIKA,Python,python,aiohttp,asyncio
Classifier: Development Status :: 3 - Alpha
Classifier: Intended Audience :: Developers
Classifier: Topic :: Software Development :: Build Tools
Classifier: License :: OSI Approved :: MIT License
Classifier: Programming Language :: Python :: Implementation :: PyPy
Classifier: Programming Language :: Python :: 3
Classifier: Programming Language :: Python :: 3.4
Classifier: Programming Language :: Python :: 3.5
Classifier: Programming Language :: Python :: 3.6
Classifier: Programming Language :: Python :: 3.7
Classifier: Programming Language :: Python :: 3.8
Classifier: Programming Language :: Python :: 3.9
Classifier: Programming Language :: Python :: 3.10
Classifier: Programming Language :: Python :: 3.11
License-File: LICENCE
Requires-Dist: pycryptodome (==3.16.0)
Requires-Dist: aiohttp (==3.8.3)
Requires-Dist: asyncio (==3.4.3)
Requires-Dist: tinytag (==1.8.1)
Requires-Dist: Pillow (==9.4.0)
